llm_tools_client/__init__.py
llm_tools_client/api_client.py
llm_tools_client/api_response.py
llm_tools_client/configuration.py
llm_tools_client/exceptions.py
llm_tools_client/py.typed
llm_tools_client/rest.py
llm_tools_client/api/__init__.py
llm_tools_client/api/category_controller_api.py
llm_tools_client/api/fewshot_controller_api.py
llm_tools_client/api/model_controller_api.py
llm_tools_client/api/prompt_controller_api.py
llm_tools_client/models/__init__.py
llm_tools_client/models/fewshot_pair_request_dto.py
llm_tools_client/models/fewshot_request_dto.py
llm_tools_client/models/model_request_dto.py
llm_tools_client/models/prompt_content_request_dto.py
llm_tools_client/models/prompt_request_dto.py
llm_tools_client/models/prompt_variable_request_dto.py
llm_tools_client-1.0.4.dist-info/METADATA
llm_tools_client-1.0.4.dist-info/WHEEL
llm_tools_client-1.0.4.dist-info/top_level.txt
llm_tools_client-1.0.4.dist-info/RECORD
