Metadata-Version: 2.4
Name: llm-tools-client
Version: 1.0.4
Summary: Python SDK for LLM Tools API
Home-page: 
Author: OpenAPI Generator community
Author-email: Koran1 <thekorani@gmail.com>
Project-URL: Repository, https://github.com/GIT_USER_ID/GIT_REPO_ID
Keywords: OpenAPI,OpenAPI-Generator,OpenAPI definition
Requires-Python: >=3.9
Requires-Dist: urllib3<3.0.0,>=2.1.0
Requires-Dist: python-dateutil>=2.8.2
Requires-Dist: pydantic>=2
Requires-Dist: typing-extensions>=4.7.1
Requires-Dist: lazy-imports<2,>=1
Dynamic: author
